odoo/addons/__init__.py
odooku_odoo_addons-11.0.7.dist-info/LICENSE
odooku_odoo_addons-11.0.7.dist-info/METADATA
odooku_odoo_addons-11.0.7.dist-info/WHEEL
odooku_odoo_addons-11.0.7.dist-info/top_level.txt
odooku_odoo_addons-11.0.7.dist-info/RECORD
