Metadata-Version: 2.1
Name: odooku-odoo-addons
Version: 11.0.7
Summary: All addons for Odoo
Home-page: https://github.com/odooku/odooku-odoo
Author: Raymond Reggers - Adaptiv Design
License: LGPLv3
Platform: UNKNOWN
Classifier: Intended Audience :: Developers
Classifier: Operating System :: OS Independent
Classifier: Programming Language :: Python
Classifier: Programming Language :: Python :: 3
Classifier: Programming Language :: Python :: 3.5
Classifier: License :: OSI Approved :: GNU Lesser General Public License v3 (LGPLv3)
Requires-Python: >=3.5
Requires-Dist: odooku-odoo-hr-holidays (==11.0.7)
Requires-Dist: odooku-odoo-base (==11.0.7)
Requires-Dist: odooku-odoo-crm (==11.0.7)
Requires-Dist: odooku-odoo-mrp-repair (==11.0.7)
Requires-Dist: odooku-odoo-purchase (==11.0.7)
Requires-Dist: odooku-odoo-account-invoicing (==11.0.7)
Requires-Dist: odooku-odoo-website-event (==11.0.7)
Requires-Dist: odooku-odoo-board (==11.0.7)
Requires-Dist: odooku-odoo-website (==11.0.7)
Requires-Dist: odooku-odoo-website-blog (==11.0.7)
Requires-Dist: odooku-odoo-sale-management (==11.0.7)
Requires-Dist: odooku-odoo-im-livechat (==11.0.7)
Requires-Dist: odooku-odoo-extra (==11.0.7)
Requires-Dist: odooku-odoo-hr-expense (==11.0.7)
Requires-Dist: odooku-odoo-mail (==11.0.7)
Requires-Dist: odooku-odoo-stock (==11.0.7)
Requires-Dist: odooku-odoo-mass-mailing (==11.0.7)
Requires-Dist: odooku-odoo-maintenance (==11.0.7)
Requires-Dist: odooku-odoo-survey (==11.0.7)
Requires-Dist: odooku-odoo-contacts (==11.0.7)
Requires-Dist: odooku-odoo-point-of-sale (==11.0.7)
Requires-Dist: odooku-odoo-website-sale (==11.0.7)
Requires-Dist: odooku-odoo-hr-recruitment (==11.0.7)
Requires-Dist: odooku-odoo-fleet (==11.0.7)
Requires-Dist: odooku-odoo-mrp (==11.0.7)
Requires-Dist: odooku-odoo-calendar (==11.0.7)
Requires-Dist: odooku-odoo-website-slides (==11.0.7)
Requires-Dist: odooku-odoo-hr-attendance (==11.0.7)
Requires-Dist: odooku-odoo-hr (==11.0.7)
Requires-Dist: odooku-odoo-lunch (==11.0.7)
Requires-Dist: odooku-odoo-hr-timesheet (==11.0.7)
Requires-Dist: odooku-odoo-project (==11.0.7)
Requires-Dist: odooku-odoo-note (==11.0.7)
Requires-Dist: odooku-odoo-website-forum (==11.0.7)
